################################### JVM 6 ###################################
ruby --bytecode example.rb 

...

  // access flags 0x9
  public static method__1$RUBY$ultimate_answer_p_(Lexample;Lorg/jruby/runtime/ThreadContext;Lorg/jruby/runtime/builtin/IRubyObject;Lorg/jruby/runtime/builtin/IRubyObject;Lorg/jruby/runtime/Block;)Lorg/jruby/runtime/builtin/IRubyObject;
  @Lorg/jruby/anno/JRubyMethod;(name="ultimate_answer?", frame=true, required=1, optional=0, rest=-1)
    ALOAD 3
    ASTORE 9
   L0
    LINENUMBER 3 L0
    ALOAD 0
    INVOKEVIRTUAL example.getCallSite0 ()Lorg/jruby/runtime/CallSite;
    ALOAD 1
    ALOAD 2
    ALOAD 0
    INVOKEVIRTUAL example.getCallSite1 ()Lorg/jruby/runtime/CallSite;
    ALOAD 1
    ALOAD 2
    ALOAD 9
    INVOKEVIRTUAL org/jruby/runtime/CallSite.call (Lorg/jruby/runtime/ThreadContext;Lorg/jruby/runtime/builtin/IRubyObject;Lorg/jruby/runtime/builtin/IRubyObject;)Lorg/jruby/runtime/builtin/IRubyObject;
    ALOAD 0
    ALOAD 1
    GETFIELD org/jruby/runtime/ThreadContext.runtime : Lorg/jruby/Ruby;
    BIPUSH 32
    INVOKEVIRTUAL example.getString0 (Lorg/jruby/Ruby;I)Lorg/jruby/RubyString;
    INVOKEVIRTUAL org/jruby/runtime/CallSite.call (Lorg/jruby/runtime/ThreadContext;Lorg/jruby/runtime/builtin/IRubyObject;Lorg/jruby/runtime/builtin/IRubyObject;Lorg/jruby/runtime/builtin/IRubyObject;)Lorg/jruby/runtime/builtin/IRubyObject;
    ARETURN
   L1
    LOCALVARIABLE value Lorg/jruby/runtime/builtin/IRubyObject; L0 L1 9
    MAXSTACK = 7
    MAXLOCALS = 10

  // access flags 0x1009
  public static method__1$RUBY$ultimate_answer_p_(Lexample;Lorg/jruby/runtime/ThreadContext;Lorg/jruby/runtime/builtin/IRubyObject;[Lorg/jruby/runtime/builtin/IRubyObject;Lorg/jruby/runtime/Block;)Lorg/jruby/runtime/builtin/IRubyObject;
    ALOAD 1
    ALOAD 3
    ICONST_1
    INVOKESTATIC org/jruby/javasupport/util/RuntimeHelpers.checkArgumentCount (Lorg/jruby/runtime/ThreadContext;[Lorg/jruby/runtime/builtin/IRubyObject;I)V
    ALOAD 0
    ALOAD 1
    ALOAD 2
    ALOAD 3
    LDC 0
    AALOAD
    ALOAD 4
    INVOKESTATIC example.method__1$RUBY$ultimate_answer_p_ (Lexample;Lorg/jruby/runtime/ThreadContext;Lorg/jruby/runtime/builtin/IRubyObject;Lorg/jruby/runtime/builtin/IRubyObject;Lorg/jruby/runtime/Block;)Lorg/jruby/runtime/builtin/IRubyObject;
    ARETURN
    MAXSTACK = 5
    MAXLOCALS = 5

