################################### JVM 6 ###################################
ruby --bytecode example.rb 
// class version 50.0 (50)
// access flags 0x21
public class example extends org/jruby/ast/executable/AbstractScript  {

  // compiled from: example.rb
  // debug info: /Users/konstantin/Workspace/presentations/example/example.rb

  // access flags 0x100A
  private static setPosition(Lorg/jruby/runtime/ThreadContext;I)V
    ALOAD 0
    LDC "example.rb"
    ILOAD 1
    INVOKEVIRTUAL org/jruby/runtime/ThreadContext.setFileAndLine (Ljava/lang/String;I)V
    RETURN
    MAXSTACK = 3
    MAXLOCALS = 2

  // access flags 0x1
  public <init>()V
    ALOAD 0
    INVOKESPECIAL org/jruby/ast/executable/AbstractScript.<init> ()V
    ALOAD 0
    LDC "example.rb"
    PUTFIELD example.filename : Ljava/lang/String;
    ALOAD 0
    NEW org/jruby/ast/executable/RuntimeCache
    DUP
    INVOKESPECIAL org/jruby/ast/executable/RuntimeCache.<init> ()V
    PUTFIELD org/jruby/ast/executable/AbstractScript.runtimeCache : Lorg/jruby/ast/executable/RuntimeCache;
    ALOAD 0
    LDC "==\uffffN\uffffto_s\uffffN\uffffultimate_answer?\uffffN\uffffnew\uffffN\uffff\u0001\u0000\u0001\u0000\u0001\u0000\u0000\u0000\u0000\u0000\u0000\u0000\u0001\u0001"
    INVOKEVIRTUAL org/jruby/ast/executable/AbstractScript.initFromDescriptor (Ljava/lang/String;)V
    ALOAD 0
    LDC 0
    LDC "ASCII-8BIT"
    INVOKEVIRTUAL org/jruby/ast/executable/AbstractScript.setEncoding (ILjava/lang/String;)V
    ALOAD 0
    LDC 0
    LDC "42"
    ALOAD 0
    INVOKEVIRTUAL example.getEncoding0 ()Lorg/jcodings/Encoding;
    INVOKEVIRTUAL org/jruby/ast/executable/AbstractScript.setByteList (ILjava/lang/String;Lorg/jcodings/Encoding;)V
    RETURN
    MAXSTACK = 4
    MAXLOCALS = 1

  // access flags 0x9
  public static __file__(Lexample;Lorg/jruby/runtime/ThreadContext;Lorg/jruby/runtime/builtin/IRubyObject;[Lorg/jruby/runtime/builtin/IRubyObject;Lorg/jruby/runtime/Block;)Lorg/jruby/runtime/builtin/IRubyObject;
  @Lorg/jruby/anno/JRubyMethod;(name="__file__", frame=true, required=0, optional=0, rest=-2)
   L0
    LINENUMBER 1 L0
    ALOAD 0
    ALOAD 1
    ALOAD 2
    GETSTATIC org/jruby/runtime/Block.NULL_BLOCK : Lorg/jruby/runtime/Block;
    INVOKESTATIC example.class_0$RUBY$DeepThought (Lexample;Lorg/jruby/runtime/ThreadContext;Lorg/jruby/runtime/builtin/IRubyObject;Lorg/jruby/runtime/Block;)Lorg/jruby/runtime/builtin/IRubyObject;
    POP
   L1
    LINENUMBER 7 L1
    ALOAD 0
    INVOKEVIRTUAL example.getCallSite2 ()Lorg/jruby/runtime/CallSite;
    ALOAD 1
    ALOAD 2
    ALOAD 0
    INVOKEVIRTUAL example.getCallSite3 ()Lorg/jruby/runtime/CallSite;
    ALOAD 1
    ALOAD 2
    ALOAD 0
    ALOAD 1
    LDC "DeepThought"
    INVOKEVIRTUAL example.getConstant0 (Lorg/jruby/runtime/ThreadContext;Ljava/lang/String;)Lorg/jruby/runtime/builtin/IRubyObject;
    INVOKEVIRTUAL org/jruby/runtime/CallSite.call (Lorg/jruby/runtime/ThreadContext;Lorg/jruby/runtime/builtin/IRubyObject;Lorg/jruby/runtime/builtin/IRubyObject;)Lorg/jruby/runtime/builtin/IRubyObject;
    ALOAD 0
    ALOAD 1
    GETFIELD org/jruby/runtime/ThreadContext.runtime : Lorg/jruby/Ruby;
    BIPUSH 42
    INVOKEVIRTUAL example.getFixnum0 (Lorg/jruby/Ruby;I)Lorg/jruby/RubyFixnum;
    INVOKEVIRTUAL org/jruby/runtime/CallSite.call (Lorg/jruby/runtime/ThreadContext;Lorg/jruby/runtime/builtin/IRubyObject;Lorg/jruby/runtime/builtin/IRubyObject;Lorg/jruby/runtime/builtin/IRubyObject;)Lorg/jruby/runtime/builtin/IRubyObject;
    ARETURN
    MAXSTACK = 9
    MAXLOCALS = 5

  // access flags 0x1
  public __file__(Lorg/jruby/runtime/ThreadContext;Lorg/jruby/runtime/builtin/IRubyObject;[Lorg/jruby/runtime/builtin/IRubyObject;Lorg/jruby/runtime/Block;)Lorg/jruby/runtime/builtin/IRubyObject;
    ALOAD 0
    ALOAD 1
    ALOAD 2
    ALOAD 3
    ALOAD 4
    INVOKESTATIC example.__file__ (Lexample;Lorg/jruby/runtime/ThreadContext;Lorg/jruby/runtime/builtin/IRubyObject;[Lorg/jruby/runtime/builtin/IRubyObject;Lorg/jruby/runtime/Block;)Lorg/jruby/runtime/builtin/IRubyObject;
    ARETURN
    MAXSTACK = 5
    MAXLOCALS = 5

  // access flags 0x9
  public static class_0$RUBY$DeepThought(Lexample;Lorg/jruby/runtime/ThreadContext;Lorg/jruby/runtime/builtin/IRubyObject;Lorg/jruby/runtime/Block;)Lorg/jruby/runtime/builtin/IRubyObject;
    TRYCATCHBLOCK L0 L1 L2 null
    ACONST_NULL
    ALOAD 1
    ALOAD 1
    GETFIELD org/jruby/runtime/ThreadContext.nil : Lorg/jruby/runtime/builtin/IRubyObject;
    INVOKESTATIC org/jruby/javasupport/util/RuntimeHelpers.prepareClassNamespace (Lorg/jruby/runtime/ThreadContext;Lorg/jruby/runtime/builtin/IRubyObject;)Lorg/jruby/RubyModule;
    SWAP
    LDC "DeepThought"
    SWAP
    INVOKEVIRTUAL org/jruby/RubyModule.defineOrGetClassUnder (Ljava/lang/String;Lorg/jruby/RubyClass;)Lorg/jruby/RubyClass;
    DUP
    ASTORE 2
    ALOAD 1
    SWAP
    ALOAD 0
    ALOAD 1
    LDC ",0,0,-1"
    INVOKEVIRTUAL example.getScope0 (Lorg/jruby/runtime/ThreadContext;Ljava/lang/String;)Lorg/jruby/parser/StaticScope;
    INVOKEVIRTUAL org/jruby/runtime/ThreadContext.preCompiledClassDummyScope (Lorg/jruby/RubyModule;Lorg/jruby/parser/StaticScope;)V
   L0
    LINENUMBER 2 L0
    ALOAD 1
    ALOAD 2
    ALOAD 0
    LDC "ultimate_answer?"
    LDC "method__1$RUBY$ultimate_answer_p_"
    LDC "value,1,0,-1"
    ICONST_1
    LDC "example.rb"
    LDC 1
    GETSTATIC org/jruby/internal/runtime/methods/CallConfiguration.FrameNoneScopeNone : Lorg/jruby/internal/runtime/methods/CallConfiguration;
    LDC "qvalue"
    INVOKESTATIC org/jruby/javasupport/util/RuntimeHelpers.def (Lorg/jruby/runtime/ThreadContext;Lorg/jruby/runtime/builtin/IRubyObject;Ljava/lang/Object;Ljava/lang/String;Ljava/lang/String;Ljava/lang/String;ILjava/lang/String;ILorg/jruby/internal/runtime/methods/CallConfiguration;Ljava/lang/String;)Lorg/jruby/runtime/builtin/IRubyObject;
   L1
    ALOAD 1
    INVOKEVIRTUAL org/jruby/runtime/ThreadContext.postCompiledClass ()V
    GOTO L3
   L2
   FRAME FULL [example org/jruby/runtime/ThreadContext org/jruby/RubyClass org/jruby/runtime/Block] [java/lang/Throwable]
    ALOAD 1
    INVOKEVIRTUAL org/jruby/runtime/ThreadContext.postCompiledClass ()V
    ATHROW
   L3
   FRAME SAME1 org/jruby/runtime/builtin/IRubyObject
    ARETURN
    MAXSTACK = 11
    MAXLOCALS = 4

  // access flags 0x9
  public static method__1$RUBY$ultimate_answer_p_(Lexample;Lorg/jruby/runtime/ThreadContext;Lorg/jruby/runtime/builtin/IRubyObject;Lorg/jruby/runtime/builtin/IRubyObject;Lorg/jruby/runtime/Block;)Lorg/jruby/runtime/builtin/IRubyObject;
  @Lorg/jruby/anno/JRubyMethod;(name="ultimate_answer?", frame=true, required=1, optional=0, rest=-1)
    ALOAD 3
    ASTORE 9
   L0
    LINENUMBER 3 L0
    ALOAD 0
    INVOKEVIRTUAL example.getCallSite0 ()Lorg/jruby/runtime/CallSite;
    ALOAD 1
    ALOAD 2
    ALOAD 0
    INVOKEVIRTUAL example.getCallSite1 ()Lorg/jruby/runtime/CallSite;
    ALOAD 1
    ALOAD 2
    ALOAD 9
    INVOKEVIRTUAL org/jruby/runtime/CallSite.call (Lorg/jruby/runtime/ThreadContext;Lorg/jruby/runtime/builtin/IRubyObject;Lorg/jruby/runtime/builtin/IRubyObject;)Lorg/jruby/runtime/builtin/IRubyObject;
    ALOAD 0
    ALOAD 1
    GETFIELD org/jruby/runtime/ThreadContext.runtime : Lorg/jruby/Ruby;
    BIPUSH 32
    INVOKEVIRTUAL example.getString0 (Lorg/jruby/Ruby;I)Lorg/jruby/RubyString;
    INVOKEVIRTUAL org/jruby/runtime/CallSite.call (Lorg/jruby/runtime/ThreadContext;Lorg/jruby/runtime/builtin/IRubyObject;Lorg/jruby/runtime/builtin/IRubyObject;Lorg/jruby/runtime/builtin/IRubyObject;)Lorg/jruby/runtime/builtin/IRubyObject;
    ARETURN
   L1
    LOCALVARIABLE value Lorg/jruby/runtime/builtin/IRubyObject; L0 L1 9
    MAXSTACK = 7
    MAXLOCALS = 10

  // access flags 0x1009
  public static method__1$RUBY$ultimate_answer_p_(Lexample;Lorg/jruby/runtime/ThreadContext;Lorg/jruby/runtime/builtin/IRubyObject;[Lorg/jruby/runtime/builtin/IRubyObject;Lorg/jruby/runtime/Block;)Lorg/jruby/runtime/builtin/IRubyObject;
    ALOAD 1
    ALOAD 3
    ICONST_1
    INVOKESTATIC org/jruby/javasupport/util/RuntimeHelpers.checkArgumentCount (Lorg/jruby/runtime/ThreadContext;[Lorg/jruby/runtime/builtin/IRubyObject;I)V
    ALOAD 0
    ALOAD 1
    ALOAD 2
    ALOAD 3
    LDC 0
    AALOAD
    ALOAD 4
    INVOKESTATIC example.method__1$RUBY$ultimate_answer_p_ (Lexample;Lorg/jruby/runtime/ThreadContext;Lorg/jruby/runtime/builtin/IRubyObject;Lorg/jruby/runtime/builtin/IRubyObject;Lorg/jruby/runtime/Block;)Lorg/jruby/runtime/builtin/IRubyObject;
    ARETURN
    MAXSTACK = 5
    MAXLOCALS = 5

  // access flags 0x9
  public static class_0$RUBY$DeepThought(Lexample;Lorg/jruby/runtime/ThreadContext;Lorg/jruby/runtime/builtin/IRubyObject;[Lorg/jruby/runtime/builtin/IRubyObject;Lorg/jruby/runtime/Block;)Lorg/jruby/runtime/builtin/IRubyObject;
    ALOAD 1
    INVOKEVIRTUAL org/jruby/runtime/ThreadContext.getRuntime ()Lorg/jruby/Ruby;
    ALOAD 3
    ICONST_0
    ICONST_0
    INVOKESTATIC org/jruby/runtime/Arity.checkArgumentCount (Lorg/jruby/Ruby;[Lorg/jruby/runtime/builtin/IRubyObject;II)I
    POP
    ALOAD 0
    ALOAD 1
    ALOAD 2
    ALOAD 4
    INVOKESTATIC example.class_0$RUBY$DeepThought (Lexample;Lorg/jruby/runtime/ThreadContext;Lorg/jruby/runtime/builtin/IRubyObject;Lorg/jruby/runtime/Block;)Lorg/jruby/runtime/builtin/IRubyObject;
    ARETURN
    MAXSTACK = 4
    MAXLOCALS = 5
}
